biolovision/__init__.py
biolovision/api.py
export_vn/__init__.py
export_vn/download_vn.py
export_vn/evnconf.py
export_vn/regulator.py
export_vn/store_all.py
export_vn/store_file.py
export_vn/store_postgresql.py
export_vn/transfer_vn.py
export_vn/data/evn_template.yaml
export_vn/locale/export_vn.pot
export_vn/locale/fr_FR/LC_MESSAGES/export_vn.mo
export_vn/locale/fr_FR/LC_MESSAGES/export_vn.po
export_vn/sql/create-vn-tables.sql
schemas/__init__.py
schemas/entities.json
schemas/families.json
schemas/field_details.json
schemas/field_groups.json
schemas/local_admin_units.json
schemas/observation.json
schemas/observers.json
schemas/places.json
schemas/species.json
schemas/taxo_groups.json
schemas/territorial_units.json
schemas/validate.py
schemas/validations.json
template/__init__.py
template/sample_app.py
update/__init__.py
update/update_vn.py
Client_API_VN-2.12.0.dist-info/AUTHORS.rst
Client_API_VN-2.12.0.dist-info/LICENSE.txt
Client_API_VN-2.12.0.dist-info/METADATA
Client_API_VN-2.12.0.dist-info/WHEEL
Client_API_VN-2.12.0.dist-info/entry_points.txt
Client_API_VN-2.12.0.dist-info/top_level.txt
Client_API_VN-2.12.0.dist-info/RECORD
