Metadata-Version: 2.1
Name: Client-API-VN
Version: 2.12.0
Summary: Python API to Biolovision API and applications using it
Home-page: https://github.com/dthonon/Client_API_VN
Author: Daniel Thonon
Author-email: d.thonon9@gmail.com
License: gpl3
Project-URL: Documentation, https://client-api-vn.readthedocs.io/en/latest/
Project-URL: BugTracker, https://github.com/dthonon/Client_API_VN/issues
Platform: any
Classifier: Programming Language :: Python :: 3 :: Only
Classifier: Programming Language :: Python :: 3.9
Classifier: Programming Language :: Python :: 3.10
Classifier: Programming Language :: Python :: 3.11
Classifier: License :: OSI Approved :: GNU General Public License v3 or later (GPLv3+)
Classifier: Operating System :: POSIX :: Linux
Classifier: Development Status :: 5 - Production/Stable
Classifier: Environment :: Console
Classifier: Topic :: Scientific/Engineering :: Bio-Informatics
Requires-Python: >=3.7
License-File: LICENSE.txt
License-File: AUTHORS.rst
Requires-Dist: SQLAlchemy <2
Requires-Dist: alembic
Requires-Dist: apscheduler ==3.9.1.post1
Requires-Dist: beautifulsoup4
Requires-Dist: docutils
Requires-Dist: jinja2
Requires-Dist: jsonschema
Requires-Dist: numpy
Requires-Dist: psutil
Requires-Dist: psycopg2-binary
Requires-Dist: pyproj
Requires-Dist: requests
Requires-Dist: requests-oauthlib
Requires-Dist: setuptools-scm
Requires-Dist: strictyaml
Requires-Dist: tabulate
Requires-Dist: towncrier
Requires-Dist: wheel
Requires-Dist: xmltodict
Requires-Dist: yappi
